ecoindex/compute/VERSION
ecoindex/compute/__init__.py
ecoindex/compute/ecoindex.py
ecoindex/data/__init__.py
ecoindex/data/colors.py
ecoindex/data/grades.py
ecoindex/data/medians.py
ecoindex/data/quantiles.py
ecoindex/data/targets.py
ecoindex/models/__init__.py
ecoindex/models/api.py
ecoindex/models/cli.py
ecoindex/models/compute.py
ecoindex/models/enums.py
ecoindex/models/response_examples.py
ecoindex/models/scraper.py
ecoindex/models/sort.py
ecoindex/models/tasks.py
ecoindex_compute-5.9.0.dist-info/METADATA
ecoindex_compute-5.9.0.dist-info/WHEEL
ecoindex_compute-5.9.0.dist-info/RECORD
