Metadata-Version: 2.3
Name: ecoindex_compute
Version: 5.9.0
Summary: Ecoindex module provides a simple way to measure the Ecoindex score based on the 3 parameters: The DOM elements of the page, the size of the page and the number of external requests of the page
License: Creative Commons BY-NC-ND
Author: Vincent Vatelot
Author-email: vincent.vatelot@ik.me
Requires-Python: >=3.10,<4.0
Classifier: License :: Other/Proprietary License
Classifier: Programming Language :: Python :: 3
Classifier: Programming Language :: Python :: 3.10
Classifier: Programming Language :: Python :: 3.11
Classifier: Programming Language :: Python :: 3.12
Classifier: Programming Language :: Python :: 3.13
Requires-Dist: aiofile (>=3.8.8,<4.0.0)
Requires-Dist: pydantic (>=2.4.2,<3.0.0)
Requires-Dist: requests (>=2.31.0,<3.0.0)
Project-URL: Homepage, http://www.ecoindex.fr
Project-URL: Repository, https://github.com/cnumr/ecoindex_python
